eth_abi_parser/__init__.py
eth_abi_parser-0.1.2.dist-info/LICENSE
eth_abi_parser-0.1.2.dist-info/METADATA
eth_abi_parser-0.1.2.dist-info/WHEEL
eth_abi_parser-0.1.2.dist-info/RECORD
