Metadata-Version: 2.1
Name: eth-abi-parser
Version: 0.1.2
Summary: A human-readable ABI parser for Ethereum smart contracts
Author: Sorawit Suriyakarn
Author-email: swit@blockpipe.io
Requires-Python: >=3.6,<4.0
Classifier: Programming Language :: Python :: 3
Classifier: Programming Language :: Python :: 3.6
Classifier: Programming Language :: Python :: 3.7
Classifier: Programming Language :: Python :: 3.8
Classifier: Programming Language :: Python :: 3.9
Classifier: Programming Language :: Python :: 3.10
Classifier: Programming Language :: Python :: 3.11
